odoo10_addon_hr_holidays_legal_leave-10.0.1.0.0-py2.7-nspkg.pth
odoo10_addon_hr_holidays_legal_leave-10.0.1.0.0.dist-info/top_level.txt
odoo10_addon_hr_holidays_legal_leave-10.0.1.0.0.dist-info/WHEEL
odoo10_addon_hr_holidays_legal_leave-10.0.1.0.0.dist-info/RECORD
odoo10_addon_hr_holidays_legal_leave-10.0.1.0.0.dist-info/metadata.json
odoo10_addon_hr_holidays_legal_leave-10.0.1.0.0.dist-info/DESCRIPTION.rst
odoo10_addon_hr_holidays_legal_leave-10.0.1.0.0.dist-info/METADATA
odoo10_addon_hr_holidays_legal_leave-10.0.1.0.0.dist-info/namespace_packages.txt
odoo/addons/hr_holidays_legal_leave/__manifest__.py
odoo/addons/hr_holidays_legal_leave/__init__.py
odoo/addons/hr_holidays_legal_leave/README.rst
odoo/addons/hr_holidays_legal_leave/models/hr_employee.py
odoo/addons/hr_holidays_legal_leave/models/hr_holidays_status.py
odoo/addons/hr_holidays_legal_leave/models/__init__.py
odoo/addons/hr_holidays_legal_leave/models/res_company.py
odoo/addons/hr_holidays_legal_leave/i18n/nl_NL.po
odoo/addons/hr_holidays_legal_leave/i18n/it.po
odoo/addons/hr_holidays_legal_leave/i18n/es.po
odoo/addons/hr_holidays_legal_leave/i18n/ar.po
odoo/addons/hr_holidays_legal_leave/i18n/ro.po
odoo/addons/hr_holidays_legal_leave/i18n/sl.po
odoo/addons/hr_holidays_legal_leave/i18n/de.po
odoo/addons/hr_holidays_legal_leave/i18n/fr.po
odoo/addons/hr_holidays_legal_leave/i18n/pt_BR.po
odoo/addons/hr_holidays_legal_leave/i18n/fi.po
odoo/addons/hr_holidays_legal_leave/views/hr_holidays_status.xml
odoo/addons/hr_holidays_legal_leave/tests/test_holidays_legal_leave.py
odoo/addons/hr_holidays_legal_leave/tests/__init__.py
odoo/addons/hr_holidays_legal_leave/static/description/icon.png
